alu.v

`timescale 1ns/100ps
module alu (
	input [31:0] r1,
	input [31:0] r2,
	input [3:0] control,
	output [31:0] result,
	output bcond
);

integer in1, in2, out;
reg bcond_w;

always @(*) 
	begin
		bcond_w = 1'b0;
		in1 = r1;
		in2 = r2;
		case(control)
			4'b0000: out = in1 + in2; //ADD and ADDI also LB, LW, SB ,SW
			4'b0001: out = in1 & in2; //AND and ANDI
			4'b0010: out = in1 | in2; //OR and ORI
			4'b0011: out = in1 << in2; //SLL, in1 shifted left by in2 amount
			4'b0100: out = (in1 < in2) ? 1 : 0; //SLT and SLTI, set on less than, output is set to 1 if in1<in2 else 0
			4'b0101: out = in1 >> in2; //SRL, in1 shifted right by in2 amount
			4'b0110: out = in1 - in2; //SUB
			4'b0111: out = in1 ^ in2; //XOR and XORI
			4'b1000: begin //BEQ, zero flag is 1 if branch is true i.e., if both inputs are equal
						if (in1 == in2) bcond_w = 1'b1;
						else bcond_w = 1'b0;
					  end
			4'b1001: begin //BNE, zero flag is 1 if branch is true i.e., if both inputs are not equal
						if (in1 != in2) bcond_w = 1'b1;
						else bcond_w = 1'b0;
					  end
			default: out = 0;
		endcase
	end
	assign bcond = bcond_w;
	assign result = out;
endmodule

mux_2x1.v

`timescale 1ns/100ps
module mux_2x1 #(parameter DATA_WIDTH = 32) (ip1, ip0, sel, out);

input [DATA_WIDTH-1:0] ip1;
input [DATA_WIDTH-1:0] ip0;
input sel;
output reg [DATA_WIDTH-1:0] out;

always@(*) begin
  if (sel==1'b1) begin
   out = ip1;
  end 
  else begin 
   out = ip0;
  end
end

endmodule

gpr.v

`timescale 1ns/100ps
module gpr(clk,RegWrite,rd_addr1,rd_addr2,wr_addr,wr_data,rd_data1,rd_data2);

input clk;
input RegWrite;
input  [4:0] rd_addr1;
input  [4:0] rd_addr2;
input  [4:0] wr_addr;
input  [31:0] wr_data;
output [31:0] rd_data1;
output [31:0] rd_data2;

parameter TD = 1;

reg  [31:0] gpr [1:31]; 

always@(posedge clk) begin
  if((RegWrite==1'b1) && (wr_addr!=5'd0)) begin
    gpr[wr_addr] <= #TD wr_data;
  end
end
    
assign rd_data1 = (rd_addr1==5'd0) ? 32'd0 : gpr[rd_addr1];   
assign rd_data2 = (rd_addr2==5'd0) ? 32'd0 : gpr[rd_addr2];

endmodule

control_unit.v

`timescale 1ns/100ps
module control_unit(opcode,funct,bcond,RegDest,ALUSrc,MemtoReg,RegWrite,MemRead,MemWrite,PCSrc1,PCSrc2,PCSrc3,isJAL,isSLL_SRL,ALU_Control);
input [5:0] opcode;       //Instr[31:26]
input [5:0] funct;        //Defines operation when Instructyion in R type
input bcond;              //1 when opcode is BEQ and BNE
output RegDest;           //Write Destination register location
                          //RegDest = 1 -> R-type - Instr[15:11]
                          //RegDest = 0 -> I-type - Instr[21:16]
output [1:0] ALUSrc;      //When Instructions is SLL or SRL, indiacated by isSLL_SRL,
                          //2nd input to ALU is SHAMT ie.,Inst[10:6]
                          //else 
                          //2nd input to ALU; ALUSrc=0-> Read data 2; ALUSrc=1->Immediate
output MemtoReg;          //Steer ALU(0)/Load memory(1) output to GPR write port
output RegWrite;          //GPR wite Disabled(0)/Enabled(1)
output MemRead;           //Read from Data memory(LW/LB=1)
output MemWrite;          //Write to Data memory(SW/SB=1)
output PCSrc1;            //PCSrc1(1)-> Next PC is Jump address
                          //PCSrc1(0)-> Next PC based on PCSrc2
output PCSrc2;            //When PCSrc1=0-->
                          //if PCSrc2=1-> Next PC based on Immediate address
                          //if PCSrc2=0-> Next PC is PC+4
output PCSrc3;            //if PCSrc3=1-> Next PC is GPR[rs]
output isJAL;             // Instruction is JAL
output isSLL_SRL;         //Set when Instruction is SLL or SRL
output [3:0] ALU_Control; //Defines the ALU operation 

`define ADD  6'b100000
`define AND  6'b100100 
`define JR   6'b001000
`define NOP  6'b000000
`define OR   6'b100101 
`define SLL  6'b000000
`define SLT  6'b101010
`define SRL  6'b000010
`define SUB  6'b100010
`define XOR  6'b100110 

`define ADDI 6'b001000
`define ANDI 6'b001100
`define BEQ  6'b000100
`define BNE  6'b000101
`define LB   6'b100000
`define LW   6'b100011
`define SB   6'b101000
`define SW   6'b101011
`define SLTI 6'b001010 
`define ORI  6'b001101
`define XORI 6'b001110

`define J    6'b000010
`define JAL  6'b000011

reg [3:0] alu_ctrl;

assign RegDest   = (opcode==6'b0);

assign ALUSrc    = (opcode!=6'b0) && (opcode!=`BEQ) && (opcode!=`BNE);

assign MemtoReg  = (opcode==`LW) || (opcode==`LB);

assign RegWrite  = (opcode!=`SW)   &&  (opcode!=`SB)  &&  
                   (opcode!=`BEQ)  &&  (opcode!=`BNE) && 
                   (opcode!=`J)    &&  
                   (!((opcode==6'd0) &&  (funct==`JR)));

assign MemRead   = (opcode==`LW)  || (opcode==`LB);

assign MemWrite  = (opcode==`SW)  || (opcode==`SB);

assign PCSrc1    = (opcode==`J)   || (opcode==`JAL);

assign PCSrc2    = ((opcode==`BEQ) || (opcode==`BNE)) && (bcond==1'b1);

assign PCSrc3    = (opcode==6'd0) && (funct==`JR); 

always@(*) begin
  casex({opcode,funct})
    {6'd0 ,`ADD},{`ADDI,6'dx},
    {`LB  ,6'dx},{`LW  ,6'dx},
    {`SB  ,6'dx},{`SW  ,6'dx} : alu_ctrl = 4'd0;
    {6'd0 ,`AND},{`ANDI,6'dx} : alu_ctrl = 4'd1;
    {6'd0 ,`OR} ,{`ORI ,6'dx} : alu_ctrl = 4'd2;
    {6'd0 ,`SLL}              : alu_ctrl = 4'd3;
    {6'd0 ,`SLT},{`SLTI,6'dx} : alu_ctrl = 4'd4;
    {6'd0 ,`SRL}              : alu_ctrl = 4'd5;
    {6'd0 ,`SUB}              : alu_ctrl = 4'd6;
    {6'd0 ,`XOR},{`XORI,6'dx} : alu_ctrl = 4'd7;
    {`BEQ ,6'dx}              : alu_ctrl = 4'd8;
    {`BNE ,6'dx}              : alu_ctrl = 4'd9;
    default                   : alu_ctrl = 4'd15;
  endcase
end

assign isJAL     = (opcode==`JAL);
assign isSLL_SRL = (opcode==6'b0) && ((funct==`SLL)||(funct==`SRL));
 
assign ALU_Control = alu_ctrl;
   
endmodule

pc.v

`timescale 1ns/100ps
module pc(clk, rst, br_signext_sl2, Inst_25_0,gpr_rd_data1, jump, branch, jump_reg, pc,pc_plus_8);

input clk, rst;
input [31:0] br_signext_sl2;
input [25:0] Inst_25_0;
input [31:0] gpr_rd_data1;
input jump;
input branch;
input jump_reg;
output [31:0] pc;
output [31:0] pc_plus_8;

parameter TD = 1;

reg  [31:0] pc_val;
wire [31:0] br_loc, pc_plus_4;



//adder next(pc_val, 32'd4, pc_plus_4);             //Adder to calculate next instruction(+4)
//adder jal (pc_val, 32'd8, pc_plus_8);             //Adder to calculate PC+8--to be 
//                                                  //written to GPR[31] on JAL
//adder br(pc_plus_4, br_signext_sl2, br_loc);      //Adder to calculate branch target

assign pc_plus_4 = pc_val + 32'd4;             // Next PC (PC+4) when the instruction  is not brach
assign pc_plus_8 = pc_val + 32'd8;             // To calculate PC+8 to be written to GPR[31] 
                                               // on JAL instruction
assign br_loc    = pc_plus_4 + br_signext_sl2; // To calculate branch target

always @ (posedge clk or posedge rst)             //PCSrc Mux
begin
  if (rst==1'b1) begin
    pc_val <= #TD 31'd0;
  end 
  else if (jump==1'b1) begin
    pc_val <= #TD {pc_plus_4[31:28],Inst_25_0,2'b00};
  end 
  else if (branch==1'b1) begin
    pc_val <= #TD br_loc;
  end
  else if(jump_reg==1'b1) begin
    pc_val <= #TD gpr_rd_data1;
  end 
  else begin
    pc_val <= #TD pc_plus_4;
  end
end


assign pc = pc_val;

endmodule

lshift.v

`timescale 1ns/100ps
module lshift (ip, op);

input [31:0] ip;
output [31:0] op;

reg [31:0] shift;

always @(ip) begin
 shift = ip << 2;
end

assign op = shift;

endmodule

signext.v

`timescale 1ns/100ps
module signext(ip, op);

input [15:0] ip;
output [31:0] op;
reg [31:0] ext;

always @(*) begin
 ext [15:0]  = ip;
 ext [31:16] = {16{ip[15]}};
end

assign op = ext;
endmodule

processor.v
`timescale 1ns/100ps
`include "file.f"
module processor (clock, reset, PC, Inst, MemRead, MemWrite, Addr, Din, Dout);

input clock, reset;
input [31:0] Inst, Dout;
output MemRead, MemWrite;
output [31:0] PC, Addr, Din;

//Register Declarations

//Wire Declarations
wire [25:0] Inst_25_0;
wire [4:0] Inst_25_21;
wire [4:0] Inst_20_16;
wire [4:0] Inst_15_11;
wire [15:0] Inst_15_0;
wire [31:0] shamt; //Shift Amount for SLL and SRL
wire [31:0] pc;        //Program Counter
wire [5:0] opcode;
wire [5:0] funct;
wire bcond;
wire RegDest;
wire ALUSrc;
wire MemtoReg;
wire RegWrite; 
wire MemRead;
wire MemWrite;
wire PCSrc1;
wire PCSrc2;
wire PCSrc3;
wire [3:0] ALU_Control;
wire [31:0] ALU_Result;
wire [31:0] ALU_datain2_src0;
wire [31:0] ALU_datain2;
wire [4:0] gpr_wr_addr;
wire [4:0] gpr_rd_addr1;
wire [4:0] gpr_wr_addr0;
wire [31:0] gpr_wr_data;
wire [31:0] gpr_rd_data1;
wire [31:0] gpr_rd_data2;
wire [31:0] mem_alu_data_out;
wire [31:0] pc_plus_8;        //PC + 8 to be written to GPR[31] on JAL
wire isJAL;    //Set when Instruction is JAL
wire isSLL_SRL;//Set when Instruction is SLL or SRL
wire [31:0] Inst_15_0_signext; 
wire [31:0] br_signext_sl2;

assign opcode = Inst[31:26];
assign funct  = Inst[5:0];
assign Inst_25_0   = Inst[25:0];
assign Inst_25_21  = Inst[25:21];
assign Inst_20_16  = Inst[20:16];
assign Inst_15_11  = Inst[15:11];
assign Inst_15_0   = Inst[15:0];
assign shamt       = {27'd0,Inst[10:6]};


//Sign extension for Instruction[15:0] for
//*branch address calculation
//*Alu source
signext signext_u0(.ip(Inst_15_0        ),
                   .op(Inst_15_0_signext)
                   );

//Left shift for branch address calculation
lshift br_lshift (.ip(Inst_15_0_signext),
                  .op(br_signext_sl2   )
                 );


//Program Counter Module with PCSrc Mux
pc pc_u0 (.clk           (clock         ),
          .rst           (reset         ), 
          .br_signext_sl2(br_signext_sl2), 
          .Inst_25_0     (Inst_25_0     ),
          .gpr_rd_data1  (gpr_rd_data1  ), 
          .jump          (PCSrc1        ), 
          .branch        (PCSrc2        ),
          .jump_reg      (PCSrc3        ),
          .pc            (pc            ),
          .pc_plus_8     (pc_plus_8     )
         );

// Control Unit
control_unit control_unit_u0(.opcode     (opcode     ),
                             .funct      (funct      ),
                             .bcond      (bcond      ),
                             .RegDest    (RegDest    ),
                             .ALUSrc     (ALUSrc     ),
                             .MemtoReg   (MemtoReg   ),
                             .RegWrite   (RegWrite   ),
                             .MemRead    (MemRead    ),
                             .MemWrite   (MemWrite   ),
                             .PCSrc1     (PCSrc1     ),
                             .PCSrc2     (PCSrc2     ),
                             .PCSrc3     (PCSrc3     ),
                             .isJAL      (isJAL      ),
                             .isSLL_SRL  (isSLL_SRL  ),
                             .ALU_Control(ALU_Control)
                            );
//Multiplexer to select write address of GPR
mux_2x1 #(.DATA_WIDTH(5)
         ) mux_2x1_u0(.ip1(Inst_15_11 ), //When Instruction is R-type
                      .ip0(Inst_20_16 ), //When Instruction is J-type 
                      .sel(RegDest    ), //1-Inst[15:0];0-Inst[20:16]
                      .out(gpr_wr_addr0)
                     );

mux_2x1 #(.DATA_WIDTH(5)
         ) mux_2x1_u1(.ip1(5'd31       ), //When JAL write PC+8 to gpr[31] 
                      .ip0(gpr_wr_addr0), 
                      .sel(isJAL       ),
                      .out(gpr_wr_addr )
                     );
                          
//Multiplexer to select write back to GPR from ALU or MEM
//Another multiplexer selects this data and JAL address(PC+8)
mux_2x1 #(.DATA_WIDTH(32)
         )mux_2x1_u2(.ip1(Dout            ), // Dout -> read data from Data memory
                     .ip0(ALU_Result      ),
                     .sel(MemtoReg        ),
                     .out(mem_alu_data_out)
                    );

mux_2x1 #(.DATA_WIDTH(32)
         )mux_2x1_u3(.ip1(pc_plus_8),
                     .ip0(mem_alu_data_out),
                     .sel(isJAL),
                     .out(gpr_wr_data)
                    );
//Read register 1 address for SLL and SRL alone is to be taken from
//Inst[20:16](Rt); others from Inst[25:21] (Rs)
mux_2x1 #(.DATA_WIDTH(5)
         )mux_2x1_u4(.ip1(Inst_20_16),
                     .ip0(Inst_25_21),
                     .sel(isSLL_SRL),
                     .out(gpr_rd_addr1)
                    );

gpr gpr_u0(.clk     (clock       ),
           .RegWrite(RegWrite    ),
           .rd_addr1(gpr_rd_addr1),
           .rd_addr2(Inst_20_16  ),
           .wr_addr (gpr_wr_addr ),
           .wr_data (gpr_wr_data ),
           .rd_data1(gpr_rd_data1),
           .rd_data2(gpr_rd_data2)
          );

//ALU operand source Mux
//Need an additional mux to input SHAMT(shift amount) for SLL and SRL
mux_2x1 #(.DATA_WIDTH(32)
         )mux_2x1_u5(.ip1(Inst_15_0_signext), 
                     .ip0(gpr_rd_data2     ), 
                     .sel(ALUSrc           ), 
                     .out(ALU_datain2_src0 )
                    );
//Mux used to take case of SLL and SRL instructions
mux_2x1 #(.DATA_WIDTH(32)
         )mux_2x1_u6 (.ip1(shamt            ), 
                      .ip0(ALU_datain2_src0 ), 
                      .sel(isSLL_SRL        ), 
                      .out(ALU_datain2      )
                     );
//ALU module
alu alu_u0(
	  .r1     (gpr_rd_data1),
	  .r2     (ALU_datain2 ),
	  .control(ALU_Control ),
	  .result (ALU_Result  ),
	  .bcond  (bcond       )
         );

assign PC = pc;
assign Din = gpr_rd_data2;
assign Addr = ALU_Result;

endmodule

test.v
`timescale 1ns/100ps
module tb_mips ();
reg          clock = 0;
reg          reset;

reg   [31:0] Inst;              // Instruction selected by PC
reg   [31:0] Dout;              // Data Memory Data out (load instruction)
wire  [31:0] PC;
wire         MemRead;           // Data Memory Read Enable
wire         MemWrite;          // Data Memory Write Enable
wire  [31:0] Addr;              // Address of Data Memory
wire  [31:0] Din;               // Data Memory Data in  (store instruction)

wire  [31:0] mem_addr;

reg   [31:0] InstMem [0:255];
reg   [31:0] DataMem [0:255];

processor P (.clock          (clock),
             .reset          (reset),
             .PC             (PC),
             .Inst           (Inst),
             .MemRead        (MemRead),
             .MemWrite       (MemWrite),
             .Addr           (Addr),
             .Din            (Din),
             .Dout           (Dout)  );

// clock
always #5 clock = ~clock;

// Instruction Moemory

always @(reset or PC) begin
   if (reset) begin
      InstMem[0]  = 32'h0;
      InstMem[1]  = 32'h20030007;       // addi   r3, r0, 7
      InstMem[2]  = 32'h00602024;       // and    r4, r3, r0
      InstMem[3]  = 32'h00032880;       // sll    r5, r3, 2
      InstMem[4]  = 32'h20060004;       // addi   r6, r0, 4
      InstMem[5]  = 32'h200c0007;       // addi   r12,r0, 7
      InstMem[6]  = 32'h200a0001;       // addi   r10,r0, 1
      InstMem[7]  = 32'h20090000;       // addi   r9, r0, 0
      InstMem[8]  = 32'h8d210004;       // lw     r1, 4($r9)
      InstMem[9]  = 32'h8d220008;       // lw     r2, 8($r9)
      InstMem[10] = 32'h0022582a;       // slt    r11,r1, r2
      InstMem[11] = 32'had210008;       // sw     r1, 8($r9)
      InstMem[12] = 32'had220004;       // sw     r2, 4($r9)
      InstMem[13] = 32'h154b0002;       // bne    r10,r11,2
      InstMem[14] = 32'had210004;       // sw     r1, 4($r9)
      InstMem[15] = 32'had220008;       // sw     r2, 8($r9)
      InstMem[16] = 32'h21290004;       // addi   r9, r9, 4
      InstMem[17] = 32'h1525fff6;       // bne    r9, r5, -10   (jump to Inst[8])
      InstMem[18] = 32'h20840001;       // addi   r4, r4, 1
      InstMem[19] = 32'h00a62822;       // sub    r5, r5, r6
      InstMem[20] = 32'h10640001;       // beq    r4, r3, 1
      InstMem[21] = 32'h01800008;       // jr     r12           (jump to Inst[7])
      InstMem[22] = 32'h0;
      InstMem[23] = 32'h0;

      Inst = 0;
   end
   else begin
      Inst = InstMem[PC>>2];
   end
end

// Data Memory
assign mem_addr = Addr >> 2;
always@(posedge clock or posedge reset) begin
  if (reset) begin
    DataMem[0]  = 32'h0;
    DataMem[1]  = 32'h00000008;
    DataMem[2]  = 32'h00000009;
    DataMem[3]  = 32'h00000007;
    DataMem[4]  = 32'h0000000a;
    DataMem[5]  = 32'h00000006;
    DataMem[6]  = 32'h00000004;
    DataMem[7]  = 32'h0000000e;
    DataMem[8]  = 32'h00000005;
    DataMem[9]  = 32'h0000000a;
    DataMem[10] = 32'h00000002;
    DataMem[11] = 32'h0000000d;
    DataMem[12] = 32'h0000000c;
    DataMem[13] = 32'h0000000b;
    DataMem[14] = 32'h0000000f;
    DataMem[15] = 32'h00000003;
    DataMem[16] = 32'h00000002;
    DataMem[17] = 32'h00000001;
  end
  else begin
    if(MemWrite) begin
      DataMem[mem_addr] = Din;
    end
  end
end
always@(*) begin
      if (MemRead) begin
         Dout = DataMem[mem_addr];
      end
end

initial begin
   #5  reset = 1;
   #10 reset = 0;
   #5500;
   #100 $finish;
end

/* display function //
always @(clock)
   $display ("time = %t, DataMemory_input = %d", $time, Din);
*/

// dumping waveform file //
initial begin
   $dumpfile("mips.vcd");
   $dumpvars(0, tb_mips);
end

endmodule

mips.vcd
$date
    Mar 20, 2015  14:35:57
$end
$version
    TOOL:	ncsim	14.10-p001
$end
$timescale
    100 ps
$end

$scope module tb_mips $end
$var reg       1 !    clock  $end
$var reg       1 "    reset  $end
$var reg      32 #    Inst [31:0] $end
$var reg      32 $    Dout [31:0] $end
$var wire     32 %    PC [31:0] $end
$var wire      1 &    MemRead  $end
$var wire      1 '    MemWrite  $end
$var wire     32 (    Addr [31:0] $end
$var wire     32 )    Din [31:0] $end
$var wire     32 *    mem_addr [31:0] $end

$scope module P $end
$var wire      1 +    clock  $end
$var wire      1 ,    reset  $end
$var wire     32 -    Inst [31:0] $end
$var wire     32 .    Dout [31:0] $end
$var wire      1 &    MemRead  $end
$var wire      1 '    MemWrite  $end
$var wire     32 %    PC [31:0] $end
$var wire     32 (    Addr [31:0] $end
$var wire     32 )    Din [31:0] $end
$var wire     26 /    Inst_25_0 [25:0] $end
$var wire      5 0    Inst_25_21 [4:0] $end
$var wire      5 1    Inst_20_16 [4:0] $end
$var wire      5 2    Inst_15_11 [4:0] $end
$var wire     16 3    Inst_15_0 [15:0] $end
$var wire     32 4    shamt [31:0] $end
$var wire     32 5    pc [31:0] $end
$var wire      6 6    opcode [5:0] $end
$var wire      6 7    funct [5:0] $end
$var wire      1 8    bcond  $end
$var wire      1 9    RegDest  $end
$var wire      1 :    ALUSrc  $end
$var wire      1 &    MemtoReg  $end
$var wire      1 ;    RegWrite  $end
$var wire      1 <    PCSrc1  $end
$var wire      1 =    PCSrc2  $end
$var wire      1 >    PCSrc3  $end
$var wire      4 ?    ALU_Control [3:0] $end
$var wire     32 @    ALU_Result [31:0] $end
$var wire     32 A    ALU_datain2_src0 [31:0] $end
$var wire     32 B    ALU_datain2 [31:0] $end
$var wire      5 C    gpr_wr_addr [4:0] $end
$var wire      5 D    gpr_rd_addr1 [4:0] $end
$var wire      5 E    gpr_wr_addr0 [4:0] $end
$var wire     32 F    gpr_wr_data [31:0] $end
$var wire     32 G    gpr_rd_data1 [31:0] $end
$var wire     32 H    gpr_rd_data2 [31:0] $end
$var wire     32 I    mem_alu_data_out [31:0] $end
$var wire     32 J    pc_plus_8 [31:0] $end
$var wire      1 K    isJAL  $end
$var wire      1 L    isSLL_SRL  $end
$var wire     32 M    Inst_15_0_signext [31:0] $end
$var wire     32 N    br_signext_sl2 [31:0] $end

$scope module signext_u0 $end
$var wire     16 3    ip [15:0] $end
$var wire     32 M    op [31:0] $end
$var reg      32 O    ext [31:0] $end
$upscope $end


$scope module br_lshift $end
$var wire     32 M    ip [31:0] $end
$var wire     32 N    op [31:0] $end
$var reg      32 P    shift [31:0] $end
$upscope $end


$scope module pc_u0 $end
$var wire      1 +    clk  $end
$var wire      1 ,    rst  $end
$var wire     32 N    br_signext_sl2 [31:0] $end
$var wire     26 /    Inst_25_0 [25:0] $end
$var wire     32 G    gpr_rd_data1 [31:0] $end
$var wire      1 <    jump  $end
$var wire      1 =    branch  $end
$var wire      1 >    jump_reg  $end
$var wire     32 5    pc [31:0] $end
$var wire     32 J    pc_plus_8 [31:0] $end
$var parameter 32 Q    TD  $end
$var reg      32 R    pc_val [31:0] $end
$var wire     32 S    br_loc [31:0] $end
$var wire     32 T    pc_plus_4 [31:0] $end
$upscope $end


$scope module control_unit_u0 $end
$var wire      6 6    opcode [5:0] $end
$var wire      6 7    funct [5:0] $end
$var wire      1 8    bcond  $end
$var wire      1 9    RegDest  $end
$var wire      1 U    ALUSrc [1] $end
$var wire      1 :    ALUSrc [0] $end
$var wire      1 &    MemtoReg  $end
$var wire      1 ;    RegWrite  $end
$var wire      1 &    MemRead  $end
$var wire      1 '    MemWrite  $end
$var wire      1 <    PCSrc1  $end
$var wire      1 =    PCSrc2  $end
$var wire      1 >    PCSrc3  $end
$var wire      1 K    isJAL  $end
$var wire      1 L    isSLL_SRL  $end
$var wire      4 ?    ALU_Control [3:0] $end
$var reg       4 V    alu_ctrl [3:0] $end
$upscope $end


$scope module mux_2x1_u0 $end
$var parameter 32 W    DATA_WIDTH  $end
$var wire      5 2    ip1 [4:0] $end
$var wire      5 1    ip0 [4:0] $end
$var wire      1 9    sel  $end
$var reg       5 X    out [4:0] $end
$upscope $end


$scope module mux_2x1_u1 $end
$var parameter 32 Y    DATA_WIDTH  $end
$var wire      5 Z    ip1 [4:0] $end
$var wire      5 E    ip0 [4:0] $end
$var wire      1 K    sel  $end
$var reg       5 [    out [4:0] $end
$upscope $end


$scope module mux_2x1_u2 $end
$var parameter 32 \    DATA_WIDTH  $end
$var wire     32 .    ip1 [31:0] $end
$var wire     32 @    ip0 [31:0] $end
$var wire      1 &    sel  $end
$var reg      32 ]    out [31:0] $end
$upscope $end


$scope module mux_2x1_u3 $end
$var parameter 32 ^    DATA_WIDTH  $end
$var wire     32 J    ip1 [31:0] $end
$var wire     32 I    ip0 [31:0] $end
$var wire      1 K    sel  $end
$var reg      32 _    out [31:0] $end
$upscope $end


$scope module mux_2x1_u4 $end
$var parameter 32 `    DATA_WIDTH  $end
$var wire      5 1    ip1 [4:0] $end
$var wire      5 0    ip0 [4:0] $end
$var wire      1 L    sel  $end
$var reg       5 a    out [4:0] $end
$upscope $end


$scope module gpr_u0 $end
$var wire      1 +    clk  $end
$var wire      1 ;    RegWrite  $end
$var wire      5 D    rd_addr1 [4:0] $end
$var wire      5 1    rd_addr2 [4:0] $end
$var wire      5 C    wr_addr [4:0] $end
$var wire     32 F    wr_data [31:0] $end
$var wire     32 G    rd_data1 [31:0] $end
$var wire     32 H    rd_data2 [31:0] $end
$var parameter 32 b    TD  $end
$upscope $end


$scope module mux_2x1_u5 $end
$var parameter 32 c    DATA_WIDTH  $end
$var wire     32 M    ip1 [31:0] $end
$var wire     32 H    ip0 [31:0] $end
$var wire      1 :    sel  $end
$var reg      32 d    out [31:0] $end
$upscope $end


$scope module mux_2x1_u6 $end
$var parameter 32 e    DATA_WIDTH  $end
$var wire     32 4    ip1 [31:0] $end
$var wire     32 A    ip0 [31:0] $end
$var wire      1 L    sel  $end
$var reg      32 f    out [31:0] $end
$upscope $end


$scope module alu_u0 $end
$var wire     32 G    r1 [31:0] $end
$var wire     32 B    r2 [31:0] $end
$var wire      4 ?    control [3:0] $end
$var wire     32 @    result [31:0] $end
$var wire      1 8    bcond  $end
$var integer  32 g    in1  $end
$var integer  32 h    in2  $end
$var integer  32 i    out  $end
$var reg       1 j    bcond_w  $end
$upscope $end

$upscope $end

$upscope $end

$enddefinitions $end
$dumpvars
b100000 e
b100000 c
b1 b
b101 `
b100000 ^
b100000 \
b101 Y
b101 W
b1 Q
0!
x"
bx #
bx $
bx %
x&
x'
bx (
bx )
b0xxxxxxxxxxxxxxxxxxxxxxxxxxxxxx *
0+
x,
bx -
bx .
bx /
bx 0
bx 1
bx 2
bx 3
b0xxxxx 4
bx 5
bx 6
bx 7
x8
x9
x:
x;
x<
x=
x>
bx ?
bx @
bx A
bx B
bx C
bx D
bx E
bx F
bx G
bx H
bx I
bx J
xK
xL
bx M
bx N
bx O
bx P
bx R
bx S
bx T
0U
bx V
bx X
b11111 Z
bx [
bx ]
bx _
bx a
bx d
bx f
bx g
bx h
bx i
xj
$end
#50
1!
1"
b0 #
1,
b0 -
1+
b0 4
b0 3
b0 2
b0 1
b0 0
b0 /
b0 7
b0 6
bx0000000000000000 O
b0 O
b0 X
b0 a
b11 V
0K
0<
0'
0&
0:
19
0=
1L
0>
1;
b11 ?
b0 D
b0 H
b0 E
b0 M
b0 [
b0 d
b0 f
0j
b0 P
b0 N
b0 )
b0 G
08
b0 B
b0 A
b0 C
b0 g
b0 h
b0 i
b0 @
b0 ]
b0 I
b0 (
b0 _
b0 *
b0 F
#60
b0 R
b1000 J
b100 T
b0 5
b0 %
b100 S
#100
0!
0+
#150
0"
1!
1+
0,
#160
b100 R
b1100 J
b1000 T
b100 5
b100 %
b1000 S
b100000000000110000000000000111 #
b100000000000110000000000000111 -
b111 3
b11 1
b110000000000000111 /
b111 7
b1000 6
b111 O
b11 a
b0 V
1:
09
0L
b0 ?
b11 D
bx H
b111 M
b111 d
b11 X
b0 a
b11100 P
b11100 N
bx )
bx G
b0 D
b11 E
b111 A
bx g
bx i
b11 [
b111 f
b111 B
b11 C
b0 G
bx @
b100100 S
b0 g
b111 h
b111 i
bx ]
bx I
bx (
b111 @
bx _
b111 ]
b111 I
b111 (
b0xxxxxxxxxxxxxxxxxxxxxxxxxxxxxx *
bx F
b111 _
b1 *
b111 F
#200
0!
0+
#250
1!
1+
#260
b1000 R
b111 H
b10000 J
b1100 T
b1000 5
b1000 %
b101000 S
b111 )
b11000000010000000100100 #
b11000000010000000100100 -
b10000000100100 3
b100 2
b0 1
b11 0
b11000000010000000100100 /
b100100 7
b0 6
b10000000100100 O
b0 X
b11 a
b1 V
0:
19
b1 ?
b11 D
b0 H
b0 E
b10000000100100 M
b0 d
b100 X
b0 i
b0 [
b1000000010010000 P
b1000000010010000 N
b0 C
b0 )
b111 G
b0 @
b100 E
b0 A
b111 g
b111 i
b0 ]
b100 [
b0 f
b0 B
b100 C
b0 I
b0 (
b111 @
b1000000010011100 S
b0 h
b0 i
b0 _
b111 ]
b111 I
b111 (
b0 *
b0 F
b0 @
b111 _
b0 ]
b0 I
b0 (
b1 *
b111 F
b0 _
b0 *
b0 F
#300
0!
0+
#350
1!
1+
#360
b1100 R
b10100 J
b10000 T
b1100 5
b1100 %
b1000000010100000 S
b110010100010000000 #
b110010100010000000 -
b10 4
b10100010000000 3
b101 2
b11 1
b0 0
b110010100010000000 /
b0 7
b10100010000000 O
b101 X
b0 a
b11 V
1L
b11 ?
b0 D
b111 H
b101 E
b10100010000000 M
b10 f
b11 a
b111 i
b111 d
b101 [
b1010001000000000 P
b1010001000000000 N
b101 C
b111 A
b111 )
b0 G
b111 @
b11 D
b10 B
b0 g
b10 h
b0 i
b111 ]
b111 G
b111 I
b111 (
b0 @
b1010001000010000 S
b111 g
b11100 i
b111 _
b0 ]
b0 I
b0 (
b1 *
b111 F
b11100 @
b0 _
b11100 ]
b11100 I
b11100 (
b0 *
b0 F
b11100 _
b111 *
b11100 F
#400
0!
0+
#450
1!
1+
#460
b10000 R
b11000 J
b10100 T
b10000 5
b10000 %
b1010001000010100 S
b100000000001100000000000000100 #
b100000000001100000000000000100 -
b0 4
b100 3
b0 2
b110 1
b1100000000000000100 /
b100 7
b1000 6
b0 f
b100 O
b0 X
b110 a
b0 V
1:
09
0L
b0 ?
b110 D
bx H
b0 E
b100 M
b0 B
b100 d
b110 X
b111 f
b0 a
b0 h
b111 i
b0 [
b10000 P
b10000 N
b0 C
bx )
bx G
b111 @
b0 D
b111 B
b110 E
b100 A
bx g
b111 h
bx i
b111 ]
b110 [
b100 f
b100 B
b110 C
b0 G
b111 I
b111 (
bx @
b100100 S
b0 g
b100 h
b100 i
b111 _
bx ]
bx I
bx (
b1 *
b111 F
b100 @
bx _
b100 ]
b100 I
b100 (
b0xxxxxxxxxxxxxxxxxxxxxxxxxxxxxx *
bx F
b100 _
b1 *
b100 F
#500
0!
0+
#550
1!
1+
#560
b10100 R
b100 H
b11100 J
b11000 T
b10100 5
b10100 %
b101000 S
b100 )
b100000000011000000000000000111 #
b100000000011000000000000000111 -
b111 3
b1100 1
b11000000000000000111 /
b111 7
b111 O
b1100 X
b1100 E
bx H
b111 M
b1100 [
b111 d
b11100 P
b11100 N
b111 A
bx )
b1100 C
b111 f
b111 B
b110100 S
b111 h
b111 i
b111 @
b111 ]
b111 I
b111 (
b111 _
b111 F
#600
0!
0+
#650
1!
1+
#660
b11000 R
b111 H
b100000 J
b11100 T
b11000 5
b11000 %
b111000 S
b111 )
b100000000010100000000000000001 #
b100000000010100000000000000001 -
b1 3
b1010 1
b10100000000000000001 /
b1 7
b1 O
b1010 X
b1010 E
bx H
b1 M
b1010 [
b1 d
b100 P
b100 N
b1 A
bx )
b1010 C
b1 f
b1 B
b100000 S
b1 h
b1 i
b1 @
b1 ]
b1 I
b1 (
b1 _
b0 *
b1 F
#700
0!
0+
#750
1!
1+
#760
b11100 R
b1 H
b100100 J
b100000 T
b11100 5
b11100 %
b100100 S
b1 )
b100000000010010000000000000000 #
b100000000010010000000000000000 -
b0 3
b1001 1
b10010000000000000000 /
b0 7
b0 O
b1001 X
b1001 E
bx H
b0 M
b1001 [
b0 d
b0 P
b0 N
b0 A
bx )
b1001 C
b0 f
b0 B
b100000 S
b0 h
b0 i
b0 @
b0 ]
b0 I
b0 (
b0 _
b0 F
#800
0!
0+
#850
1!
1+
